saccharide/__init__.py
saccharide/_version.py
saccharide/stubs.py
saccharide/sugarmodule.py
saccharide/wrappers.py
python_saccharide-0.0.1.dist-info/LICENSE
python_saccharide-0.0.1.dist-info/METADATA
python_saccharide-0.0.1.dist-info/WHEEL
python_saccharide-0.0.1.dist-info/top_level.txt
python_saccharide-0.0.1.dist-info/RECORD
