Metadata-Version: 2.1
Name: python-saccharide
Version: 0.0.1
Summary: Syntactical sugar and other hacks for python
Home-page: https://github.com/MishaKlopukh/python-saccharide/
Author: Misha Klopukh
Author-email: mishakmak@gmail.com
License: UNKNOWN
Project-URL: Bug Tracker, https://github.com/MishaKlopukh/python-saccharide/issues
Platform: UNKNOWN
Classifier: Programming Language :: Python :: 3
Classifier: License :: OSI Approved :: MIT License
Classifier: Operating System :: OS Independent
Requires-Python: >=3.8
License-File: LICENSE
